{
  "version": "1.0.0",
  "vendor": "Umbra Space",
  "imagingMode": "SPOTLIGHT",
  "orderType": "SNAPSHOT",
  "productSku": "UMB-SPOTLIGHT-50-1",
  "baseIpr": 0.5,
  "targetIpr": 0.5,
  "umbraSatelliteName": "UMBRA_05",
  "collects": [
    {
      "id": "ea1fe3ba-4d50-4184-ab46-d493bcb3f34c",
      "taskId": "c63eb04a-5e6e-4e06-8691-3636442665a0",
      "revisitId": null,
      "startAtUTC": "2023-05-18T15:21:37.941140+00:00",
      "endAtUTC": "2023-05-18T15:21:42.684455+00:00",
      "radarBand": "X",
      "radarCenterFrequencyHz": 9599996231.147087,
      "polarizations": [
        "VV"
      ],
      "angleAzimuthDegrees": -46.44585657984791,
      "angleGrazingDegrees": 25.187974871545553,
      "angleIncidenceDegrees": 64.81202512845445,
      "angleSquintDegrees": 30.75943993537471,
      "slantRangeMeters": 1067317.4866060799,
      "antennaGainDb": 0.0,
      "satelliteTrack": "DESCENDING",
      "observationDirection": "LEFT",
      "timeOfCenterOfAperturePolynomial": {
        "Coefs": [
          [
            2.390246330540625
          ]
        ]
      },
      "sceneCenterPointLla": {
        "type": "Point",
        "coordinates": [
          -79.58138191548136,
          8.9736682707277,
          -0.34274612024795176
        ]
      },
      "footprintPolygonLla": {
        "type": "Polygon",
        "coordinates": [
          [
            [
              -79.5821847595969,
              8.999229414475703,
              0.2926056291908026
            ],
            [
              -79.58529946125016,
              8.995933288860083,
              0.15386797115206718
            ],
            [
              -79.58841100727656,
              8.992638331060995,
              0.054494419135153294
            ],
            [
              -79.59152518500966,
              8.989343936237143,
              -0.005499792285263538
            ],
            [
              -79.59463888946044,
              8.986047897475956,
              -0.026209458708763123
            ],
            [
              -79.5977525465145,
              8.982755225972,
              -0.007509187795221806
            ],
            [
              -79.60086262805204,
              8.97945869598546,
              0.050324163399636745
            ],
            [
              -79.60397845630352,
              8.976164934029017,
              0.1477337507531047
            ],
            [
              -79.60709071873879,
              8.972867307483977,
              0.28432427160441875
            ],
            [
              -79.60377725993354,
              8.969773385111782,
              0.146757154725492
            ],
            [
              -79.60046159447856,
              8.966676960903769,
              0.04843320604413748
            ],
            [
              -79.59714992815437,
              8.963582459546375,
              -0.01046054158359766
            ],
            [
              -79.59383335804277,
              8.960488264793245,
              -0.03020275104790926
            ],
            [
              -79.59051768091709,
              8.957393782501859,
              -0.010586939752101898
            ],
            [
              -79.58720559510564,
              8.954296201416104,
              0.04851018916815519
            ],
            [
              -79.58389170281885,
              8.951201142581874,
              0.146808460354805
            ],
            [
              -79.58057870125734,
              8.948105795912179,
              0.2844313383102417
            ],
            [
              -79.57746665645908,
              8.951403117436026,
              0.1466611586511135
            ],
            [
              -79.57435104389828,
              8.95469657069284,
              0.04842793010175228
            ],
            [
              -79.57124116174316,
              8.957992790479842,
              -0.01065795123577118
            ],
            [
              -79.5681250098451,
              8.961287963533383,
              -0.030253595672547817
            ],
            [
              -79.56501417470554,
              8.964580880080218,
              -0.010606944561004639
            ],
            [
              -79.56190016729762,
              8.96787496515928,
              0.048420085571706295
            ],
            [
              -79.55878609459943,
              8.97117242787599,
              0.1467620898038149
            ],
            [
              -79.55567422178919,
              8.974465430971856,
              0.28436047211289406
            ],
            [
              -79.55898701123496,
              8.977561118680574,
              0.14782929327338934
            ],
            [
              -79.56230069706744,
              8.980656508157185,
              0.05056828539818525
            ],
            [
              -79.56561528002796,
              8.983751599496802,
              -0.007411550730466843
            ],
            [
              -79.56892808205293,
              8.986849205518899,
              -0.025963944382965565
            ],
            [
              -79.57224446265585,
              8.989943699717056,
              -0.005348418839275837
            ],
            [
              -79.57555595665684,
              8.993038503614553,
              0.05466810707002878
            ],
            [
              -79.57887146186421,
              8.996135210357918,
              0.15402558539062738
            ],
            [
              -79.5821847595969,
              8.999229414475703,
              0.2926056291908026
            ]
          ]
        ]
      },
      "maxGroundResolution": {
        "azimuthMeters": 0.47367086620055865,
        "rangeMeters": 0.46063800425007567
      }
    }
  ],
  "derivedProducts": {
    "GEC": [
      {
        "numRows": 13082,
        "numColumns": 13083,
        "groundResolution": {
          "azimuthMeters": 0.5137981972934622,
          "rangeMeters": 0.5137985674537529
        },
        "looks": {
          "azimuth": 1.0,
          "range": 1.0424495787415828
        }
      }
    ],
    "SICD": [
      {
        "numRows": 10183,
        "numColumns": 11089,
        "groundResolution": {
          "azimuthMeters": 0.4817017072134645,
          "rangeMeters": 0.46208666977609386
        },
        "slantResolution": {
          "azimuthMeters": 0.45751030088501193,
          "rangeMeters": 0.4181498030582762
        },
        "apertureReferencePointPolynomial": {
          "X": {
            "Coefs": [
              516581.119430916,
              -1357.1870868340407,
              -0.459142950943732,
              0.00047456072238013933,
              -5.574656434457599e-11,
              1.0318342322200603e-11
            ]
          },
          "Y": {
            "Coefs": [
              -6657686.957448474,
              -2011.6611172125995,
              4.125730550805663,
              0.0004251280339334789,
              -3.089886234501271e-11,
              -1.4617833239295713e-11
            ]
          },
          "Z": {
            "Coefs": [
              1733921.6988436214,
              -7290.397752502376,
              -1.0563188265939516,
              0.0014810673484513047,
              2.908901980890134e-10,
              -1.5468844754870155e-11
            ]
          }
        }
      }
    ]
  }
}