{
  "version": "1.0.0",
  "vendor": "Umbra Space",
  "imagingMode": "SPOTLIGHT",
  "orderType": "SNAPSHOT",
  "productSku": "UMB-SPOTLIGHT-50-1",
  "baseIpr": 0.5,
  "targetIpr": 0.5,
  "umbraSatelliteName": "UMBRA_04",
  "collects": [
    {
      "id": "9c66d05c-4c78-4082-af68-545125d7c986",
      "taskId": "e83adf4d-72bc-49cf-8d01-4270dcd94108",
      "revisitId": null,
      "startAtUTC": "2023-05-09T14:46:38.255886+00:00",
      "endAtUTC": "2023-05-09T14:46:40.738191+00:00",
      "radarBand": "X",
      "radarCenterFrequencyHz": 9599985169.479624,
      "polarizations": [
        "VV"
      ],
      "angleAzimuthDegrees": 59.13260414223281,
      "angleGrazingDegrees": 60.16012098967838,
      "angleIncidenceDegrees": 29.839879010321617,
      "angleSquintDegrees": 41.738656133028705,
      "slantRangeMeters": 585591.0376978577,
      "antennaGainDb": 0.0,
      "satelliteTrack": "DESCENDING",
      "observationDirection": "RIGHT",
      "timeOfCenterOfAperturePolynomial": {
        "Coefs": [
          [
            1.2475086488660243
          ]
        ]
      },
      "sceneCenterPointLla": {
        "type": "Point",
        "coordinates": [
          -79.58138191548136,
          8.9736682707277,
          -0.34274612024795176
        ]
      },
      "footprintPolygonLla": {
        "type": "Polygon",
        "coordinates": [
          [
            [
              -79.5749260390639,
              8.998422020874234,
              0.28818236384540796
            ],
            [
              -79.57884312698211,
              8.996129900753093,
              0.15077493619173765
            ],
            [
              -79.58276441433479,
              8.993838775773055,
              0.052645571529865265
            ],
            [
              -79.58668445076992,
              8.99154829245955,
              -0.006192500703036785
            ],
            [
              -79.59060085524882,
              8.98925440295081,
              -0.02593901287764311
            ],
            [
              -79.59452146904307,
              8.986961507322897,
              -0.006319715641438961
            ],
            [
              -79.59844086671617,
              8.984669260010287,
              0.052563038654625416
            ],
            [
              -79.60235906595403,
              8.982377666099362,
              0.15067487582564354
            ],
            [
              -79.60628148627798,
              8.980087068261652,
              0.2882417403161526
            ],
            [
              -79.60397483036657,
              8.976189050487177,
              0.1503296783193946
            ],
            [
              -79.601671296665,
              8.972293809349043,
              0.051946334540843964
            ],
            [
              -79.59936305190159,
              8.968396937675259,
              -0.007234970107674599
            ],
            [
              -79.59705549265469,
              8.964498761986349,
              -0.026960007846355438
            ],
            [
              -79.59475106385229,
              8.960603341546786,
              -0.0072479937225580215
            ],
            [
              -79.59244731946842,
              8.956706599674572,
              0.05187988746911287
            ],
            [
              -79.59013880574491,
              8.952808190084681,
              0.15036742389202118
            ],
            [
              -79.58783887864229,
              8.948912849554832,
              0.28825410548597574
            ],
            [
              -79.58391718797354,
              8.951204379016755,
              0.14994551613926888
            ],
            [
              -79.57999976370976,
              8.953496899689688,
              0.05088264588266611
            ],
            [
              -79.57608113971298,
              8.955790071231409,
              -0.008951043710112572
            ],
            [
              -79.5721588134794,
              8.958079818885015,
              -0.02935484517365694
            ],
            [
              -79.56824322767066,
              8.960374626830816,
              -0.010768427513539791
            ],
            [
              -79.56432392242027,
              8.962666009242525,
              0.047241426073014736
            ],
            [
              -79.56040336413787,
              8.96495803056228,
              0.14454564359039068
            ],
            [
              -79.55648705095295,
              8.967251042097047,
              0.2809169767424464
            ],
            [
              -79.5587917638901,
              8.971145798009625,
              0.14401376247406006
            ],
            [
              -79.56109410089829,
              8.975042932525968,
              0.046561772003769875
            ],
            [
              -79.56339710894443,
              8.978938750045314,
              -0.011557959951460361
            ],
            [
              -79.56570323688457,
              8.982837315881214,
              -0.030367051251232624
            ],
            [
              -79.56801003690629,
              8.986734582176926,
              -0.00980338267982006
            ],
            [
              -79.5703175202162,
              8.990630559745354,
              0.05011234525591135
            ],
            [
              -79.57262022361725,
              8.994524901068285,
              0.14943569712340832
            ],
            [
              -79.5749260390639,
              8.998422020874234,
              0.28818236384540796
            ]
          ]
        ]
      },
      "maxGroundResolution": {
        "azimuthMeters": 0.5709375385703052,
        "rangeMeters": 0.5588165632326713
      }
    }
  ],
  "derivedProducts": {
    "GEC": [
      {
        "numRows": 7414,
        "numColumns": 7414,
        "groundResolution": {
          "azimuthMeters": 0.809314421021959,
          "rangeMeters": 0.809314305273684
        },
        "looks": {
          "azimuth": 1.0,
          "range": 1.0437033994474512
        }
      }
    ],
    "SICD": [
      {
        "numRows": 8640,
        "numColumns": 13385,
        "groundResolution": {
          "azimuthMeters": 0.5844758325470919,
          "rangeMeters": 0.5600017679972061
        },
        "slantResolution": {
          "azimuthMeters": 0.45794970560131,
          "rangeMeters": 0.2786444604505414
        },
        "apertureReferencePointPolynomial": {
          "X": {
            "Coefs": [
              1473350.330131081,
              -1171.0167208229016,
              -1.014257679430878,
              0.0004396738938310367,
              -1.0501671015073356e-06,
              1.713274904170583e-07
            ]
          },
          "Y": {
            "Coefs": [
              -6619958.603534461,
              -1644.961738123537,
              4.103485691669978,
              0.00036917172037712065,
              4.0576597145862555e-06,
              -6.648687232795837e-07
            ]
          },
          "Z": {
            "Coefs": [
              1224436.8082668446,
              -7420.497988042765,
              -0.7485939943826089,
              0.0015143481247623942,
              -6.880293265431081e-07,
              1.1350904549812812e-07
            ]
          }
        }
      }
    ]
  }
}