{
  "version": "1.0.0",
  "vendor": "Umbra Space",
  "imagingMode": "SPOTLIGHT",
  "orderType": "SNAPSHOT",
  "productSku": "UMB-SPOTLIGHT-50-1",
  "baseIpr": 0.5,
  "targetIpr": 0.5,
  "umbraSatelliteName": "UMBRA_05",
  "collects": [
    {
      "id": "7ce3d890-5e59-458e-8c5f-4d680520f22d",
      "taskId": "079cf5b6-09d0-477b-94d7-b1a816a78be5",
      "revisitId": null,
      "startAtUTC": "2023-07-02T14:44:04.810100+00:00",
      "endAtUTC": "2023-07-02T14:44:07.599877+00:00",
      "radarBand": "X",
      "radarCenterFrequencyHz": 9599987505.23664,
      "polarizations": [
        "VV"
      ],
      "angleAzimuthDegrees": 57.728336929804456,
      "angleGrazingDegrees": 52.517157402187344,
      "angleIncidenceDegrees": 37.482842597812656,
      "angleSquintDegrees": 44.82052230834961,
      "slantRangeMeters": 640997.7366363837,
      "antennaGainDb": 0.0,
      "satelliteTrack": "DESCENDING",
      "observationDirection": "RIGHT",
      "timeOfCenterOfAperturePolynomial": {
        "Coefs": [
          [
            1.8876459734105568
          ]
        ]
      },
      "sceneCenterPointLla": {
        "type": "Point",
        "coordinates": [
          -79.58138191548136,
          8.9736682707277,
          -0.34274612024795176
        ]
      },
      "footprintPolygonLla": {
        "type": "Polygon",
        "coordinates": [
          [
            [
              -79.55622629177621,
              8.968337856939309,
              0.2807850297540426
            ],
            [
              -79.55869836394656,
              8.972129089193261,
              0.14401022531092167
            ],
            [
              -79.56117258091086,
              8.97592169810544,
              0.04649305064231157
            ],
            [
              -79.56364893604623,
              8.979715689511988,
              -0.011706139892339706
            ],
            [
              -79.56612152027589,
              8.983508169423882,
              -0.03041219338774681
            ],
            [
              -79.56859624708811,
              8.987302044550143,
              -0.009777635335922241
            ],
            [
              -79.5710712506581,
              8.991094376280122,
              0.050195252522826195
            ],
            [
              -79.57354839550463,
              8.994888117210687,
              0.14956971537321806
            ],
            [
              -79.57602180759214,
              8.998680375351062,
              0.28832562547177076
            ],
            [
              -79.57983390762129,
              8.996219177561805,
              0.15084293205291033
            ],
            [
              -79.58365131599172,
              8.993760529254391,
              0.05272368807345629
            ],
            [
              -79.58746632389253,
              8.991298589311045,
              -0.0062416838482022285
            ],
            [
              -79.59127863633901,
              8.988839303005633,
              -0.02588909398764372
            ],
            [
              -79.59509442356422,
              8.986379628651017,
              -0.006227729842066765
            ],
            [
              -79.59890968683268,
              8.983919618520186,
              0.05269148573279381
            ],
            [
              -79.60272443484502,
              8.981459275764118,
              0.15086292196065187
            ],
            [
              -79.60653867627182,
              8.97899860353335,
              0.2882811492308974
            ],
            [
              -79.60406313960318,
              8.97520400862931,
              0.15041903965175152
            ],
            [
              -79.60159163082287,
              8.971413784557924,
              0.05210359860211611
            ],
            [
              -79.59911456054729,
              8.967619117461513,
              -0.0070386119186878204
            ],
            [
              -79.59664152601518,
              8.963828810811275,
              -0.026719365268945694
            ],
            [
              -79.59416689670148,
              8.960033985043554,
              -0.006994730792939663
            ],
            [
              -79.59169042249711,
              8.956240608758202,
              0.05205183103680611
            ],
            [
              -79.5892161073528,
              8.952448616533271,
              0.15047751646488905
            ],
            [
              -79.58674395785388,
              8.948658002553522,
              0.288222249597311
            ],
            [
              -79.58292988258619,
              8.951118052226096,
              0.14984789304435253
            ],
            [
              -79.57911529669938,
              8.953577774439282,
              0.050750575959682465
            ],
            [
              -79.57530019138781,
              8.956037166002398,
              -0.00906363595277071
            ],
            [
              -79.57148455781483,
              8.95849622372417,
              -0.02958847861737013
            ],
            [
              -79.56767028537767,
              8.960957899917771,
              -0.010939001105725765
            ],
            [
              -79.56385356768892,
              8.963416278990023,
              0.047134832479059696
            ],
            [
              -79.56004222959167,
              8.965877216345081,
              0.14423517882823944
            ],
            [
              -79.55622629177621,
              8.968337856939309,
              0.2807850297540426
            ]
          ]
        ]
      },
      "maxGroundResolution": {
        "azimuthMeters": 0.4234715733997829,
        "rangeMeters": 0.4323071517095181
      }
    }
  ],
  "derivedProducts": {
    "GEC": [
      {
        "numRows": 10058,
        "numColumns": 10057,
        "groundResolution": {
          "azimuthMeters": 0.5965928636211352,
          "rangeMeters": 0.5965947705080445
        },
        "looks": {
          "azimuth": 1.0,
          "range": 1.0024845888408325
        }
      }
    ],
    "SICD": [
      {
        "numRows": 11278,
        "numColumns": 17259,
        "groundResolution": {
          "azimuthMeters": 0.4349386823794974,
          "rangeMeters": 0.4338621036307813
        },
        "slantResolution": {
          "azimuthMeters": 0.34421036073420863,
          "rangeMeters": 0.2640154287995955
        },
        "apertureReferencePointPolynomial": {
          "X": {
            "Coefs": [
              1550893.821114904,
              -1137.1214161631585,
              -1.0645953789523188,
              0.00042875993708381296,
              -1.9801592032668994e-09,
              2.3802812602356955e-10
            ]
          },
          "Y": {
            "Coefs": [
              -6596021.293469165,
              -1721.235283966261,
              4.076727500065153,
              0.0003952780593602022,
              3.349303022119751e-09,
              -3.582431857733729e-10
            ]
          },
          "Z": {
            "Coefs": [
              1287325.3310649677,
              -7405.104168874705,
              -0.7851283815455317,
              0.0015059709787528892,
              1.1762619136456146e-09,
              -1.254094232216434e-10
            ]
          }
        }
      }
    ]
  }
}